LICENSE.txt
README.md
pyproject.toml
setup.cfg
setup.py
dtrv/__init__.py
dtrv/util.py
dtrv/version.py
dtrv.egg-info/PKG-INFO
dtrv.egg-info/SOURCES.txt
dtrv.egg-info/dependency_links.txt
dtrv.egg-info/requires.txt
dtrv.egg-info/top_level.txt
dtrv.egg-info/zip-safe
dtrv/v1/Method.py
dtrv/v1/__init__.py