Metadata-Version: 2.1
Name: dtrv
Version: 0.0.2
Summary: Python client library for the dtrv
Author: dtrv
Author-email: hotstoneio@qq.com
License: UNKNOWN
Platform: UNKNOWN
Classifier: Programming Language :: Python :: 3
Classifier: License :: OSI Approved :: MIT License
Classifier: Operating System :: OS Independent
Requires-Python: >=3.7.1
License-File: LICENSE.txt
